Pikachu_Kit-0.1.0.data/data/Lib/site-packages/SourceHanSerifSC-Bold.otf
Pikachu_Kit-0.1.0.data/data/Lib/site-packages/unrar.exe
sdk/__init__.py
sdk/setting.py
sdk/base/base_bos.py
sdk/base/base_db.py
sdk/base/base_tables.py
sdk/base/base_temp.py
sdk/plugins/SourceHanSerifSC-Bold.otf
sdk/plugins/unrar.exe
sdk/temp/temp_get_mark_opt.py
sdk/temp/temp_secret_code.py
sdk/temp/temp_selenium.py
sdk/temp/temp_supports.py
sdk/tools/JsonTextGride.py
sdk/tools/download.py
sdk/tools/load_env.py
sdk/tools/make_download_urls.py
sdk/tools/many_single.py
sdk/tools/merge_excel.py
sdk/tools/pcapng_raw.py
sdk/tools/sql_file.py
sdk/tools/sql_select.py
sdk/tools/tools_file_split.py
sdk/tools/tools_find_face.py
sdk/tools/tools_merge_files.py
sdk/tools/tools_others.py
sdk/tools/tools_voice_tran.py
sdk/utils/util_bos.py
sdk/utils/util_class.py
sdk/utils/util_cmd.py
sdk/utils/util_compress.py
sdk/utils/util_csv.py
sdk/utils/util_db.py
sdk/utils/util_decorate.py
sdk/utils/util_email.py
sdk/utils/util_encrypt.py
sdk/utils/util_excel.py
sdk/utils/util_file.py
sdk/utils/util_folder.py
sdk/utils/util_img.py
sdk/utils/util_json.py
sdk/utils/util_jsonl.py
sdk/utils/util_log.py
sdk/utils/util_map.py
sdk/utils/util_network.py
sdk/utils/util_platform.py
sdk/utils/util_secret.py
sdk/utils/util_single.py
sdk/utils/util_times.py
sdk/utils/util_translate.py
sdk/utils/util_video.py
sdk/utils/util_voice.py
Pikachu_Kit-0.1.0.dist-info/METADATA
Pikachu_Kit-0.1.0.dist-info/WHEEL
Pikachu_Kit-0.1.0.dist-info/top_level.txt
Pikachu_Kit-0.1.0.dist-info/RECORD
