Metadata-Version: 2.1
Name: Pikachu_Kit
Version: 0.1.0
Summary: Pikachu_Kit
Author: JHC
Author-email: JHC000abc@gmail.com
Classifier: Programming Language :: Python :: 3
Classifier: License :: OSI Approved :: MIT License
Classifier: Operating System :: OS Independent
Requires-Dist: pycryptodome ==3.19.0
Requires-Dist: bce-python-sdk ==0.8.97
Requires-Dist: cup ==3.2.32
Requires-Dist: unrar ==0.4
Requires-Dist: PyMySQL ==1.1.0
Requires-Dist: opencv-python ==4.8.1.78
Requires-Dist: selenium-wire ==5.1.0
Requires-Dist: selenium ==4.15.2
Requires-Dist: lxml ==4.9.1
Requires-Dist: python-dotenv ==1.0.0
Requires-Dist: requests ==2.31.0
Requires-Dist: rarfile ==4.1
Requires-Dist: XlsxWriter ==3.1.9
Requires-Dist: xlrd ==2.0.1
Requires-Dist: chardet ==5.2.0
Requires-Dist: numpy
Requires-Dist: nb-log ==10.6
Requires-Dist: urllib3 ==2.1.0
Requires-Dist: python-dateutil ==2.8.2
Requires-Dist: zhconv ==1.4.3
Requires-Dist: pypinyin ==0.49.0
Requires-Dist: pydub ==0.25.1
Requires-Dist: passlib ==1.7.4
Requires-Dist: python-jose ==3.3.0
Requires-Dist: pyotp ==2.9.0
Requires-Dist: schedule
Requires-Dist: pyinstaller
Requires-Dist: sqlalchemy
Requires-Dist: mysql-connector-python
Requires-Dist: webdriver-manager
Requires-Dist: python-nmap
Requires-Dist: Pillow
Requires-Dist: pandas
Requires-Dist: DrissionPage
